{
  "regions": {
    "New England": [
      "CT",
      "ME",
      "MA",
      "NH",
      "RI",
      "VT"
    ],
    "Mid-Atlantic": [
      "DE",
      "MD",
      "NJ",
      "NY",
      "PA"
    ],
    "South": [
      "AL",
      "AR",
      "FL",
      "GA",
      "KY",
      "LA",
      "MS",
      "MO",
      "NC",
      "SC",
      "TN",
      "VA",
      "WV"
    ],
    "Midwest": [
      "IL",
      "IN",
      "IA",
      "KS",
      "MI",
      "MN",
      "NE",
      "ND",
      "OH",
      "SD",
      "WI"
    ],
    "Southwest": [
      "AZ",
      "NM",
      "OK",
      "TX"
    ],
    "West": [
      "AK",
      "CA",
      "CO",
      "HI",
      "ID",
      "MT",
      "NV",
      "OR",
      "UT",
      "WA",
      "WY"
    ],
    "Federal": [
      "US"
    ]
  },
  "state_regions": {
    "CT": "New England",
    "ME": "New England",
    "MA": "New England",
    "NH": "New England",
    "RI": "New England",
    "VT": "New England",
    "DE": "Mid-Atlantic",
    "MD": "Mid-Atlantic",
    "NJ": "Mid-Atlantic",
    "NY": "Mid-Atlantic",
    "PA": "Mid-Atlantic",
    "AL": "South",
    "AR": "South",
    "FL": "South",
    "GA": "South",
    "KY": "South",
    "LA": "South",
    "MS": "South",
    "MO": "South",
    "NC": "South",
    "SC": "South",
    "TN": "South",
    "VA": "South",
    "WV": "South",
    "IL": "Midwest",
    "IN": "Midwest",
    "IA": "Midwest",
    "KS": "Midwest",
    "MI": "Midwest",
    "MN": "Midwest",
    "NE": "Midwest",
    "ND": "Midwest",
    "OH": "Midwest",
    "SD": "Midwest",
    "WI": "Midwest",
    "AZ": "Southwest",
    "NM": "Southwest",
    "OK": "Southwest",
    "TX": "Southwest",
    "AK": "West",
    "CA": "West",
    "CO": "West",
    "HI": "West",
    "ID": "West",
    "MT": "West",
    "NV": "West",
    "OR": "West",
    "UT": "West",
    "WA": "West",
    "WY": "West",
    "US": "Federal"
  }
}